luigi_soft_failures/__init__.py
luigi_soft_failures/config.py
luigi_soft_failures/soft_failure.py
luigi_soft_failures/utils.py
luigi_soft_failures-0.1.1.dist-info/LICENSE
luigi_soft_failures-0.1.1.dist-info/METADATA
luigi_soft_failures-0.1.1.dist-info/WHEEL
luigi_soft_failures-0.1.1.dist-info/top_level.txt
luigi_soft_failures-0.1.1.dist-info/RECORD
