Metadata-Version: 2.1
Name: luigi-soft-failures
Version: 0.1.1
Summary: Allow Luigi tasks to fail softly, without cancelling downstream tasks.
Home-page: https://github.com/maxhollmann/luigi_soft_failures
Author: Max Hollmann
Author-email: maxhollmann@gmail.com
License: MIT
Platform: UNKNOWN
Classifier: License :: OSI Approved :: MIT License
Classifier: Programming Language :: Python
Classifier: Programming Language :: Python :: 3
Classifier: Programming Language :: Python :: 3 :: Only
Classifier: Programming Language :: Python :: 3.6
Classifier: Programming Language :: Python :: Implementation :: CPython
Classifier: Programming Language :: Python :: Implementation :: PyPy
Requires-Python: >=3.6.0
